README.txt
setup.py
scripts/wmi-query
wmi_query/__init__.py
wmi_query/wmi_conn.py
wmi_query/wmi_parse.py
wmi_query/wmi_query.py
wmi_query.egg-info/PKG-INFO
wmi_query.egg-info/SOURCES.txt
wmi_query.egg-info/dependency_links.txt
wmi_query.egg-info/requires.txt
wmi_query.egg-info/top_level.txt