Metadata-Version: 1.0
Name: wmi-query
Version: 0.1.4
Summary: A simple way to convert wmi data from wmi class objects into defaultdict.
Home-page: https://github.com/kanazux/wmi-query
Author: Silvio AS a.k.a kanazuchi
Author-email: alvolivre@live.com
License: BSD2CLAUSE
Keywords: wmi impacket
Platform: UNKNOWN
